kirchhoff/__init__.py
kirchhoff/circuit_dual.py
kirchhoff/circuit_flow.py
kirchhoff/circuit_flux.py
kirchhoff/circuit_init.py
kirchhoff/draw_networkx.py
kirchhoff/init_crystal.py
kirchhoff/init_dual.py
kirchhoff/init_random.py
kirchhoff-0.1.1.dist-info/LICENSE
kirchhoff-0.1.1.dist-info/METADATA
kirchhoff-0.1.1.dist-info/WHEEL
kirchhoff-0.1.1.dist-info/top_level.txt
kirchhoff-0.1.1.dist-info/RECORD
